GoWebBiancheng/README.md
GoWebBiancheng/__init__.py
GoWebBiancheng/__main__.py
GoWebBiancheng/file.epub
GoWebBiancheng/index.html
GoWebBiancheng/css/__init__.py
GoWebBiancheng/css/annotations.css
GoWebBiancheng/css/main.css
GoWebBiancheng/css/normalize.css
GoWebBiancheng/css/popup.css
GoWebBiancheng/font/__init__.py
GoWebBiancheng/font/fontello.eot
GoWebBiancheng/font/fontello.svg
GoWebBiancheng/font/fontello.ttf
GoWebBiancheng/font/fontello.woff
GoWebBiancheng/img/__init__.py
GoWebBiancheng/img/annotator-glyph-sprite.png
GoWebBiancheng/img/annotator-icon-sprite.png
GoWebBiancheng/img/apple-touch-icon.png
GoWebBiancheng/img/cancelfullscreen.png
GoWebBiancheng/img/close.png
GoWebBiancheng/img/fullscreen.png
GoWebBiancheng/img/loader.gif
GoWebBiancheng/img/menu-icon.png
GoWebBiancheng/img/save.png
GoWebBiancheng/img/saved.png
GoWebBiancheng/img/settings-s.png
GoWebBiancheng/img/settings.png
GoWebBiancheng/img/star.png
GoWebBiancheng/js/__init__.py
GoWebBiancheng/js/epub.js
GoWebBiancheng/js/epub.min.js
GoWebBiancheng/js/epub.min.map
GoWebBiancheng/js/hooks.min.js
GoWebBiancheng/js/hooks.min.map
GoWebBiancheng/js/reader.js
GoWebBiancheng/js/reader.js.map
GoWebBiancheng/js/reader.min.js
GoWebBiancheng/js/reader.min.map
GoWebBiancheng/js/hooks/__init__.py
GoWebBiancheng/js/hooks/extensions/__init__.py
GoWebBiancheng/js/hooks/extensions/highlight.js
GoWebBiancheng/js/libs/__init__.py
GoWebBiancheng/js/libs/jquery.min.js
GoWebBiancheng/js/libs/localforage.min.js
GoWebBiancheng/js/libs/screenfull.js
GoWebBiancheng/js/libs/screenfull.min.js
GoWebBiancheng/js/libs/zip.min.js
GoWebBiancheng/js/plugins/__init__.py
GoWebBiancheng/js/plugins/hypothesis.js
GoWebBiancheng/js/plugins/search.js
go_web_biancheng-2024.3.6.0.dist-info/METADATA
go_web_biancheng-2024.3.6.0.dist-info/WHEEL
go_web_biancheng-2024.3.6.0.dist-info/entry_points.txt
go_web_biancheng-2024.3.6.0.dist-info/top_level.txt
go_web_biancheng-2024.3.6.0.dist-info/RECORD
